gachi/__init__.py
gachi/__main__.py
gachi/data/fisting-is-$300.mp3
gachi/data/fucking-slaves.mp3
gachi/data/rip-the-skin.mp3
gachi/data/semen.mp3
gachi/data/suck-some-dick.mp3
gachi/data/swallow-cum.mp3
gachi/data/turns-me-on.mp3
gachi/data/van.mp3
gachi/data/woo.mp3
gachi/data/yes-sir.mp3
gachi-3.0.dist-info/entry_points.txt
gachi-3.0.dist-info/WHEEL
gachi-3.0.dist-info/METADATA
gachi-3.0.dist-info/RECORD
