Metadata-Version: 2.1
Name: gachi
Version: 3.0
Summary: A useful tool for anal practice
Author: Anonymous
Author-email: anal@gadgets.com
Requires-Python: >=3.7,<4.0
Classifier: Programming Language :: Python :: 3
Classifier: Programming Language :: Python :: 3.7
Classifier: Programming Language :: Python :: 3.8
Classifier: Programming Language :: Python :: 3.9
Requires-Dist: pyglet (>=1.5.18,<2.0.0)
